tests/__init__.py
tests/test_facts.py
useless_facts/__init__.py
useless_facts/facts.py
useless_facts_package-1.0.0.dist-info/licenses/LICENSE
useless_facts_package-1.0.0.dist-info/METADATA
useless_facts_package-1.0.0.dist-info/WHEEL
useless_facts_package-1.0.0.dist-info/top_level.txt
useless_facts_package-1.0.0.dist-info/RECORD
